sphinx/__init__.py
sphinx/__main__.py
sphinx/addnodes.py
sphinx/application.py
sphinx/config.py
sphinx/deprecation.py
sphinx/errors.py
sphinx/events.py
sphinx/extension.py
sphinx/highlighting.py
sphinx/io.py
sphinx/jinja2glue.py
sphinx/parsers.py
sphinx/project.py
sphinx/py.typed
sphinx/pygments_styles.py
sphinx/registry.py
sphinx/roles.py
sphinx/theming.py
sphinx/versioning.py
sphinx/_cli/__init__.py
sphinx/_cli/util/__init__.py
sphinx/_cli/util/colour.py
sphinx/_cli/util/errors.py
sphinx/builders/__init__.py
sphinx/builders/_epub_base.py
sphinx/builders/changes.py
sphinx/builders/dirhtml.py
sphinx/builders/dummy.py
sphinx/builders/epub3.py
sphinx/builders/gettext.py
sphinx/builders/linkcheck.py
sphinx/builders/manpage.py
sphinx/builders/singlehtml.py
sphinx/builders/texinfo.py
sphinx/builders/text.py
sphinx/builders/xml.py
sphinx/builders/html/__init__.py
sphinx/builders/html/_assets.py
sphinx/builders/html/_build_info.py
sphinx/builders/latex/__init__.py
sphinx/builders/latex/constants.py
sphinx/builders/latex/nodes.py
sphinx/builders/latex/theming.py
sphinx/builders/latex/transforms.py
sphinx/builders/latex/util.py
sphinx/cmd/__init__.py
sphinx/cmd/build.py
sphinx/cmd/make_mode.py
sphinx/cmd/quickstart.py
sphinx/directives/__init__.py
sphinx/directives/admonitions.py
sphinx/directives/code.py
sphinx/directives/other.py
sphinx/directives/patches.py
sphinx/domains/__init__.py
sphinx/domains/_domains_container.py
sphinx/domains/_index.py
sphinx/domains/changeset.py
sphinx/domains/citation.py
sphinx/domains/index.py
sphinx/domains/javascript.py
sphinx/domains/math.py
sphinx/domains/rst.py
sphinx/domains/c/__init__.py
sphinx/domains/c/_ast.py
sphinx/domains/c/_ids.py
sphinx/domains/c/_parser.py
sphinx/domains/c/_symbol.py
sphinx/domains/cpp/__init__.py
sphinx/domains/cpp/_ast.py
sphinx/domains/cpp/_ids.py
sphinx/domains/cpp/_parser.py
sphinx/domains/cpp/_symbol.py
sphinx/domains/python/__init__.py
sphinx/domains/python/_annotations.py
sphinx-9.0.3.dist-info/entry_points.txt
sphinx-9.0.3.dist-info/licenses/LICENSE.rst
sphinx-9.0.3.dist-info/WHEEL
sphinx-9.0.3.dist-info/METADATA
sphinx-9.0.3.dist-info/RECORD
