Metadata-Version: 2.4
Name: Sphinx
Version: 9.0.3
Summary: Python documentation generator
Author-email: Adam Turner <aa-turner@users.noreply.github.com>, Georg Brandl <georg@python.org>
Requires-Python: >=3.11
License-Expression: BSD-2-Clause
Classifier: Development Status :: 5 - Production/Stable
Classifier: Environment :: Console
Classifier: Environment :: Web Environment
Classifier: Intended Audience :: Developers
Classifier: Intended Audience :: Education
Classifier: Intended Audience :: End Users/Desktop
Classifier: Intended Audience :: Information Technology
Classifier: Intended Audience :: Other Audience
Classifier: Intended Audience :: Science/Research
Classifier: Intended Audience :: System Administrators
Classifier: Operating System :: OS Independent
Classifier: Programming Language :: Python
Classifier: Programming Language :: Python :: 3
Classifier: Programming Language :: Python :: 3 :: Only
Classifier: Programming Language :: Python :: 3.11
Classifier: Programming Language :: Python :: 3.12
Classifier: Programming Language :: Python :: 3.13
Classifier: Programming Language :: Python :: 3.14
Classifier: Programming Language :: Python :: 3.15
Classifier: Programming Language :: Python :: Implementation :: CPython
Classifier: Programming Language :: Python :: Implementation :: PyPy
Classifier: Framework :: Sphinx
Classifier: Framework :: Sphinx :: Domain
Classifier: Framework :: Sphinx :: Extension
Classifier: Framework :: Sphinx :: Theme
Classifier: Topic :: Documentation
Classifier: Topic :: Documentation :: Sphinx
Classifier: Topic :: Education
Classifier: Topic :: Internet :: WWW/HTTP :: Site Management
Classifier: Topic :: Internet :: WWW/HTTP :: Site Management :: Link Checking
Classifier: Topic :: Printing
Classifier: Topic :: Software Development
Classifier: Topic :: Software Development :: Documentation
Classifier: Topic :: Text Editors :: Documentation
Classifier: Topic :: Text Processing
Classifier: Topic :: Text Processing :: General
Classifier: Topic :: Text Processing :: Indexing
Classifier: Topic :: Text Processing :: Markup
Classifier: Topic :: Text Processing :: Markup :: HTML
Classifier: Topic :: Text Processing :: Markup :: LaTeX
Classifier: Topic :: Text Processing :: Markup :: Markdown
Classifier: Topic :: Text Processing :: Markup :: reStructuredText
Classifier: Topic :: Text Processing :: Markup :: XML
Classifier: Topic :: Utilities
Classifier: Typing :: Typed
License-File: LICENSE.rst
Requires-Dist: sphinxcontrib-applehelp>=1.0.7
Requires-Dist: sphinxcontrib-devhelp>=1.0.6
Requires-Dist: sphinxcontrib-htmlhelp>=2.0.6
Requires-Dist: sphinxcontrib-jsmath>=1.0.1
Requires-Dist: sphinxcontrib-qthelp>=1.0.6
Requires-Dist: sphinxcontrib-serializinghtml>=1.1.9
Requires-Dist: Jinja2>=3.1
Requires-Dist: Pygments>=2.17
Requires-Dist: docutils>=0.20,<0.23
Requires-Dist: snowballstemmer>=2.2
Requires-Dist: babel>=2.13
Requires-Dist: alabaster>=0.7.14
Requires-Dist: imagesize>=1.3
Requires-Dist: requests>=2.30.0
Requires-Dist: roman-numerals>=1.0.0
Requires-Dist: packaging>=23.0
Requires-Dist: colorama>=0.4.6; sys_platform == 'win32'
Project-URL: Changelog, https://www.sphinx-doc.org/en/master/changes.html
Project-URL: Code, https://github.com/sphinx-doc/sphinx
Project-URL: Documentation, https://www.sphinx-doc.org/
Project-URL: Download, https://pypi.org/project/Sphinx/
Project-URL: Homepage, https://www.sphinx-doc.org/
Project-URL: Issue tracker, https://github.com/sphinx-doc/sphinx/issues
